postdantic/__init__.py
postdantic/model_helpers.py
postdantic-0.0.3.dist-info/LICENSE
postdantic-0.0.3.dist-info/METADATA
postdantic-0.0.3.dist-info/WHEEL
postdantic-0.0.3.dist-info/top_level.txt
postdantic-0.0.3.dist-info/RECORD
