Metadata-Version: 2.1
Name: postdantic
Version: 0.0.3
Summary: ORM for Postgres using pydantic
Author-email: Omer Cohen <omercotkd@gmail.com>
Project-URL: Homepage, https://github.com/omercotkd/postdantic
Project-URL: Bug Tracker, https://github.com/omercotkd/postdantic/issues
Classifier: Programming Language :: Python :: 3
Classifier: License :: OSI Approved :: MIT License
Classifier: Operating System :: OS Independent
Requires-Python: >=3.10
License-File: LICENSE
